transformers_js/__init__.py
transformers_js_py/__init__.py
transformers_js_py/_version.py
transformers_js_py/audio.py
transformers_js_py/lazy_import_proxies.py
transformers_js_py/proxies.py
transformers_js_py/url.py
transformers_js_py-0.19.10.dist-info/METADATA
transformers_js_py-0.19.10.dist-info/WHEEL
transformers_js_py-0.19.10.dist-info/licenses/LICENSE
transformers_js_py-0.19.10.dist-info/RECORD
