Metadata-Version: 2.4
Name: transformers-js-py
Version: 0.19.10
Project-URL: repository, https://github.com/whitphx/transformers.js.py
Author-email: "Yuichiro Tachibana (Tsuchiya)" <t.yic.yt@gmail.com>
License: Apache-2.0
License-File: LICENSE
Requires-Python: >=3.10
Provides-Extra: audio
Requires-Dist: numpy>=2.1.2; extra == 'audio'
Requires-Dist: scipy>=1.14.0; extra == 'audio'
